{
"type": "FeatureCollection",
"name": "Hotels",
"crs": { "type": "name", "properties": { "name": "urn:ogc:def:crs:OGC:1.3:CRS84" } },
"features": [
{ "type": "Feature", "properties": { "ID": 5342524424.0, "BizType": "food_court", "BizName": "Hill Top", "Address1": null, "Address2": null, "PostalBox": null, "City": null, "Tel": null, "Email": null, "Website": "food", "Remarks": null }, "geometry": { "type": "Point", "coordinates": [ 30.9173783, 3.01192169968131 ] } }
]
}
